mlsconverters/__init__.py
mlsconverters/common.py
mlsconverters/decorators.py
mlsconverters/io.py
mlsconverters/keras.py
mlsconverters/models.py
mlsconverters/session.py
mlsconverters/sklearn.py
mlsconverters/xgboost.py
tests/__init__.py
tests/test_keras.py
tests/test_model.py
aqschema_converters-0.1.0.dist-info/LICENSE
aqschema_converters-0.1.0.dist-info/METADATA
aqschema_converters-0.1.0.dist-info/WHEEL
aqschema_converters-0.1.0.dist-info/top_level.txt
aqschema_converters-0.1.0.dist-info/RECORD
